{"cameraMode":{"drawMode":0,"name":"Shaded","section":"Shading Mode"},"sceneLighting":false,"audioPlay":false,"sceneViewState":{"showFog":true,"showMaterialUpdate":false,"showSkybox":false,"showFlares":true,"showImageEffects":true,"showParticleSystems":true,"showVisualEffectGraphs":true,"m_FxEnabled":true},"in2DMode":false,"pivot":{"x":-42.29999923706055,"y":4.4292192459106449,"z":30.299999237060548},"rotation":{"x":0.14399170875549317,"y":0.48914608359336855,"z":-0.08225501328706742,"w":0.8562957644462586},"size":8.171868324279786,"orthographic":false}